{
  "timestamp": "2026-04-26T13:22:08.247079",
  "stocks": [
    {
      "price": 274500,
      "volume": 186903,
      "market_cap": 13.01,
      "day_change": 3.0,
      "week_change": 4.97,
      "month_change": 9.58,
      "high_52w": 393000,
      "low_52w": 208500,
      "from_high": -30.15,
      "ma5": 264600.0,
      "ma20": 250050.0,
      "ma60": 245792.0,
      "cross_signal": null,
      "rsi": 78.4,
      "short_ratio": 0,
      "foreign_net": 0,
      "institution_net": 0,
      "code": "259960",
      "name": "크래프톤"
    },
    {
      "price": 270500,
      "volume": 90413,
      "market_cap": 5.83,
      "day_change": -0.18,
      "week_change": 1.12,
      "month_change": 21.85,
      "high_52w": 282000,
      "low_52w": 144000,
      "from_high": -4.08,
      "ma5": 268800.0,
      "ma20": 241150.0,
      "ma60": 227693.0,
      "cross_signal": null,
      "rsi": 78.9,
      "short_ratio": 0,
      "foreign_net": 0,
      "institution_net": 0,
      "code": "036570",
      "name": "엔씨소프트"
    },
    {
      "price": 50400,
      "volume": 171054,
      "market_cap": 4.13,
      "day_change": 1.51,
      "week_change": -2.14,
      "month_change": 1.31,
      "high_52w": 69000,
      "low_52w": 43500,
      "from_high": -26.96,
      "ma5": 50650.0,
      "ma20": 50335.0,
      "ma60": 52451.0,
      "cross_signal": null,
      "rsi": 54.0,
      "short_ratio": 0,
      "foreign_net": 0,
      "institution_net": 0,
      "code": "251270",
      "name": "넷마블"
    },
    {
      "price": 57000,
      "volume": 794083,
      "market_cap": 3.66,
      "day_change": 2.52,
      "week_change": 5.56,
      "month_change": -15.68,
      "high_52w": 77400,
      "low_52w": 29000,
      "from_high": -26.36,
      "ma5": 55740.0,
      "ma20": 59195.0,
      "ma60": 56173.0,
      "cross_signal": null,
      "rsi": 41.1,
      "short_ratio": 0,
      "foreign_net": 0,
      "institution_net": 0,
      "code": "263750",
      "name": "펄어비스"
    },
    {
      "price": 12350,
      "volume": 141880,
      "market_cap": 1.11,
      "day_change": -0.64,
      "week_change": -1.04,
      "month_change": -0.16,
      "high_52w": 23600,
      "low_52w": 11450,
      "from_high": -47.67,
      "ma5": 12458.0,
      "ma20": 12186.0,
      "ma60": 13862.0,
      "cross_signal": null,
      "rsi": 66.4,
      "short_ratio": 0,
      "foreign_net": 0,
      "institution_net": 0,
      "code": "293490",
      "name": "카카오게임즈"
    },
    {
      "price": 12100,
      "volume": 70580,
      "market_cap": 0.8,
      "day_change": 0.67,
      "week_change": 0.17,
      "month_change": 4.49,
      "high_52w": 18420,
      "low_52w": 10310,
      "from_high": -34.31,
      "ma5": 12066.0,
      "ma20": 11761.0,
      "ma60": 11801.0,
      "cross_signal": null,
      "rsi": 68.1,
      "short_ratio": 0,
      "foreign_net": 0,
      "institution_net": 0,
      "code": "225570",
      "name": "넥슨게임즈"
    },
    {
      "price": 23150,
      "volume": 185004,
      "market_cap": 0.79,
      "day_change": 1.09,
      "week_change": -10.79,
      "month_change": 11.03,
      "high_52w": 43500,
      "low_52w": 19320,
      "from_high": -46.78,
      "ma5": 23980.0,
      "ma20": 21525.0,
      "ma60": 24429.0,
      "cross_signal": null,
      "rsi": 66.1,
      "short_ratio": 0,
      "foreign_net": 0,
      "institution_net": 0,
      "code": "112040",
      "name": "위메이드"
    },
    {
      "price": 32200,
      "volume": 65624,
      "market_cap": 0.76,
      "day_change": 0.0,
      "week_change": -3.74,
      "month_change": 3.87,
      "high_52w": 63200,
      "low_52w": 28400,
      "from_high": -49.05,
      "ma5": 32790.0,
      "ma20": 31455.0,
      "ma60": 35887.0,
      "cross_signal": null,
      "rsi": 63.4,
      "short_ratio": 0,
      "foreign_net": 0,
      "institution_net": 0,
      "code": "376300",
      "name": "디어유"
    },
    {
      "price": 23700,
      "volume": 40609,
      "market_cap": 0.51,
      "day_change": 1.28,
      "week_change": -0.63,
      "month_change": -2.07,
      "high_52w": 31550,
      "low_52w": 22500,
      "from_high": -24.88,
      "ma5": 23640.0,
      "ma20": 23672.0,
      "ma60": 25784.0,
      "cross_signal": null,
      "rsi": 59.4,
      "short_ratio": 0,
      "foreign_net": 0,
      "institution_net": 0,
      "code": "095660",
      "name": "네오위즈"
    },
    {
      "price": 23750,
      "volume": 106861,
      "market_cap": 0.29,
      "day_change": -0.42,
      "week_change": -3.65,
      "month_change": -17.39,
      "high_52w": 58200,
      "low_52w": 21750,
      "from_high": -59.19,
      "ma5": 24070.0,
      "ma20": 24095.0,
      "ma60": 33772.0,
      "cross_signal": null,
      "rsi": 53.2,
      "short_ratio": 0,
      "foreign_net": 0,
      "institution_net": 0,
      "code": "194480",
      "name": "데브시스터즈"
    }
  ],
  "leader": {
    "price": 274500,
    "volume": 186903,
    "market_cap": 13.01,
    "day_change": 3.0,
    "week_change": 4.97,
    "month_change": 9.58,
    "high_52w": 393000,
    "low_52w": 208500,
    "from_high": -30.15,
    "ma5": 264600.0,
    "ma20": 250050.0,
    "ma60": 245792.0,
    "cross_signal": null,
    "rsi": 78.4,
    "short_ratio": 0,
    "foreign_net": 0,
    "institution_net": 0,
    "code": "259960",
    "name": "크래프톤"
  }
}