{
  "timestamp": "2026-02-09T07:11:16.286819",
  "stocks": [
    {
      "price": 236500,
      "volume": 185117,
      "market_cap": 11.21,
      "day_change": -0.63,
      "week_change": -3.67,
      "month_change": 0.21,
      "high_52w": 393000,
      "low_52w": 225000,
      "from_high": -39.82,
      "ma5": 240500.0,
      "ma20": 243550.0,
      "ma60": 247192.0,
      "cross_signal": null,
      "rsi": 48.2,
      "short_ratio": 0,
      "foreign_net": 0,
      "institution_net": 0,
      "code": "259960",
      "name": "크래프톤"
    },
    {
      "price": 55500,
      "volume": 281463,
      "market_cap": 4.77,
      "day_change": 1.46,
      "week_change": 7.35,
      "month_change": 13.03,
      "high_52w": 69000,
      "low_52w": 37500,
      "from_high": -19.57,
      "ma5": 52860.0,
      "ma20": 51675.0,
      "ma60": 51032.0,
      "cross_signal": null,
      "rsi": 63.8,
      "short_ratio": 0,
      "foreign_net": 0,
      "institution_net": 0,
      "code": "251270",
      "name": "넷마블"
    },
    {
      "price": 203000,
      "volume": 461102,
      "market_cap": 4.37,
      "day_change": -6.24,
      "week_change": -4.92,
      "month_change": -9.17,
      "high_52w": 258500,
      "low_52w": 134600,
      "from_high": -21.47,
      "ma5": 211500.0,
      "ma20": 228300.0,
      "ma60": 214662.0,
      "cross_signal": null,
      "rsi": 29.6,
      "short_ratio": 0,
      "foreign_net": 0,
      "institution_net": 0,
      "code": "036570",
      "name": "엔씨소프트"
    },
    {
      "price": 53700,
      "volume": 352701,
      "market_cap": 3.45,
      "day_change": 0.75,
      "week_change": 2.29,
      "month_change": 37.34,
      "high_52w": 59500,
      "low_52w": 28750,
      "from_high": -9.75,
      "ma5": 53000.0,
      "ma20": 47935.0,
      "ma60": 41091.0,
      "cross_signal": null,
      "rsi": 75.0,
      "short_ratio": 0,
      "foreign_net": 0,
      "institution_net": 0,
      "code": "263750",
      "name": "펄어비스"
    },
    {
      "price": 15720,
      "volume": 185479,
      "market_cap": 1.41,
      "day_change": 2.48,
      "week_change": -2.78,
      "month_change": 8.79,
      "high_52w": 23600,
      "low_52w": 12900,
      "from_high": -33.39,
      "ma5": 15804.0,
      "ma20": 15510.0,
      "ma60": 15603.0,
      "cross_signal": null,
      "rsi": 60.0,
      "short_ratio": 0,
      "foreign_net": 0,
      "institution_net": 0,
      "code": "293490",
      "name": "카카오게임즈"
    },
    {
      "price": 29800,
      "volume": 140914,
      "market_cap": 1.01,
      "day_change": 5.67,
      "week_change": 1.02,
      "month_change": 6.43,
      "high_52w": 44600,
      "low_52w": 23500,
      "from_high": -33.18,
      "ma5": 29240.0,
      "ma20": 28840.0,
      "ma60": 27322.0,
      "cross_signal": null,
      "rsi": 61.4,
      "short_ratio": 0,
      "foreign_net": 0,
      "institution_net": 0,
      "code": "112040",
      "name": "위메이드"
    },
    {
      "price": 42750,
      "volume": 325895,
      "market_cap": 1.01,
      "day_change": 4.14,
      "week_change": 16.17,
      "month_change": 18.42,
      "high_52w": 63200,
      "low_52w": 30650,
      "from_high": -32.36,
      "ma5": 40390.0,
      "ma20": 36438.0,
      "ma60": 35300.0,
      "cross_signal": null,
      "rsi": 67.8,
      "short_ratio": 0,
      "foreign_net": 0,
      "institution_net": 0,
      "code": "376300",
      "name": "디어유"
    },
    {
      "price": 12490,
      "volume": 251929,
      "market_cap": 0.82,
      "day_change": -0.16,
      "week_change": -2.04,
      "month_change": 0.4,
      "high_52w": 18420,
      "low_52w": 11450,
      "from_high": -32.19,
      "ma5": 12598.0,
      "ma20": 12620.0,
      "ma60": 12645.0,
      "cross_signal": null,
      "rsi": 52.4,
      "short_ratio": 0,
      "foreign_net": 0,
      "institution_net": 0,
      "code": "225570",
      "name": "넥슨게임즈"
    },
    {
      "price": 28750,
      "volume": 83598,
      "market_cap": 0.63,
      "day_change": 4.17,
      "week_change": 0.0,
      "month_change": 13.64,
      "high_52w": 31550,
      "low_52w": 18670,
      "from_high": -8.87,
      "ma5": 28320.0,
      "ma20": 27555.0,
      "ma60": 25960.0,
      "cross_signal": null,
      "rsi": 62.1,
      "short_ratio": 0,
      "foreign_net": 0,
      "institution_net": 0,
      "code": "095660",
      "name": "네오위즈"
    },
    {
      "price": 39100,
      "volume": 186407,
      "market_cap": 0.47,
      "day_change": 5.11,
      "week_change": 3.99,
      "month_change": 25.32,
      "high_52w": 58200,
      "low_52w": 28450,
      "from_high": -32.82,
      "ma5": 37160.0,
      "ma20": 35892.0,
      "ma60": 32768.0,
      "cross_signal": null,
      "rsi": 62.5,
      "short_ratio": 0,
      "foreign_net": 0,
      "institution_net": 0,
      "code": "194480",
      "name": "데브시스터즈"
    }
  ],
  "leader": {
    "price": 236500,
    "volume": 185117,
    "market_cap": 11.21,
    "day_change": -0.63,
    "week_change": -3.67,
    "month_change": 0.21,
    "high_52w": 393000,
    "low_52w": 225000,
    "from_high": -39.82,
    "ma5": 240500.0,
    "ma20": 243550.0,
    "ma60": 247192.0,
    "cross_signal": null,
    "rsi": 48.2,
    "short_ratio": 0,
    "foreign_net": 0,
    "institution_net": 0,
    "code": "259960",
    "name": "크래프톤"
  }
}